.gitignore
.prospector.yaml
.pylintrc
LICENSE
MANIFEST.in
README.rst
requirements.in
requirements.txt
run.sh
setup.cfg
setup.py
versioneer.py
qworkerd/__init__.py
qworkerd/_version.py
qworkerd/logs.py
qworkerd/main.py
qworkerd/manage.py
qworkerd/qwtask.py
qworkerd/retryhandler.py
qworkerd/sentryhandler.py
qworkerd/settings.py
qworkerd/tasks.py
qworkerd/urls.py
qworkerd.egg-info/PKG-INFO
qworkerd.egg-info/SOURCES.txt
qworkerd.egg-info/dependency_links.txt
qworkerd.egg-info/entry_points.txt
qworkerd.egg-info/not-zip-safe
qworkerd.egg-info/pbr.json
qworkerd.egg-info/requires.txt
qworkerd.egg-info/top_level.txt
qworkerd/_cfgtool/install
qworkerd/_cfgtool/logging.conf.templ
qworkerd/_cfgtool/qworkerd
qworkerd/_cfgtool/qworkerd.conf.templ
qworkerd/_cfgtool/qworkerd.upstart.conf.templ