Metadata-Version: 1.1
Name: qworkerd
Version: 0.3.post1
Summary: Celery based worker (default/pluggable)
Home-page: https://github.com/clearclaw/qworkerd
Author: J C Lawrence
Author-email: claw@kanga.nu
License: LGPL v3.0
Keywords: celery,worker
Platform: UNKNOWN
Classifier: Development Status :: 4 - Beta
Classifier: Intended Audience :: Developers
Classifier: License :: OSI Approved :: GNU Lesser General Public License v3 or later (LGPLv3+)
Classifier: Topic :: Utilities
